cap_naive_bayes/__init__.py
cap_naive_bayes/naive_bayes.py
cap_naive_bayes-0.1.3.dist-info/METADATA
cap_naive_bayes-0.1.3.dist-info/WHEEL
cap_naive_bayes-0.1.3.dist-info/licenses/LICENSE
cap_naive_bayes-0.1.3.dist-info/RECORD
