Metadata-Version: 2.4
Name: cap-naive-bayes
Version: 0.1.3
Summary: A lightweight implementation of a multinomial Naive Bayes classifier for Annotation Transfer of single-cell data.
License-File: LICENSE
Requires-Python: >=3.11
Requires-Dist: numpy>=2.0.0
Requires-Dist: pandas>=2.0.0
Requires-Dist: pyarrow>=21.0.0
Requires-Dist: scipy>=1.16.0
